{"kind":"identitytoolkit#DownloadAccountResponse","users":[{"localId":"yPr6hO4LCT4CIT51STHak5DOgthN","lastLoginAt":"1750659829910","displayName":"anna_chen","photoUrl":"","emailVerified":true,"email":"anna@example.com","salt":"fakeSaltKGlkmLGetBWC7p5MZAn3","passwordHash":"fakeHash:salt=fakeSaltKGlkmLGetBWC7p5MZAn3:password=123456","passwordUpdatedAt":1750588309714,"validSince":"1750588309","createdAt":"1750587094514","providerUserInfo":[{"providerId":"password","email":"anna@example.com","federatedId":"anna@example.com","rawId":"anna@example.com","displayName":"anna_chen","photoUrl":""}],"initialEmail":"anna@example.com","customAttributes":"","lastRefreshAt":"2025-06-24T13:47:01.218Z"}]}